cwl_testrunner/__init__.py
cwl_testrunner/skeleton.py
cwl_testrunner-0.0.1.dist-info/LICENSE.txt
cwl_testrunner-0.0.1.dist-info/METADATA
cwl_testrunner-0.0.1.dist-info/WHEEL
cwl_testrunner-0.0.1.dist-info/top_level.txt
cwl_testrunner-0.0.1.dist-info/RECORD
